Workbook

Sheet 使用说明
B1: 生意快启 · 首年现金流三情景推演
B4: 这份表回答一个问题：产品做出来之后，钱从哪里来、多久能回本。
B6: 【怎么用】
B7: 1. 先看「三情景对比」：一眼看清三种结果的差距。
B8: 2. 再看「打平计算器」：算出你每月至少要有多少访客才不亏钱。
B9: 3. 然后改「悲观 / 中性 / 乐观」三个工作表里的黄色格子。
B10: 4. 最后回到「参数」表调整单价与成本，全表自动重算。
B12: 【颜色说明】
B13: 黄色 = 你可以改的输入值；橙色 = 成本发生变化的月份；蓝色 = 表头。
B15: 【三个必须记住的结论】
B16: 一、三种情景的差别 100% 来自「月访客数 × 转化率」，与代码写得多快完全无关。
B17: 二、客单价在三个情景里只差 1.75 倍，月营收却差 40 倍——差距全部由获客和转化拉开。
... B25: 所有行业基准值见「参数」表下半部分，来源已在《现金流推演与认知修正 V1.0》附录 A 逐条列出。

Sheet 参数
A1: 参数与假设（黄色可改）
A3: 单笔变动成本（元/单） | B3: 3 | C3: AI 生成成本，见《产品需求文档》第 15 章成本模型
A4: 月固定成本·基础（元） | B4: 1200 | C4: AI 工具订阅 + 服务器 + 域名；参考独立开发者约 120 美元/月
A5: 月固定成本·加大投入（元） | B5: 3500 | C5: 第 7 个月起（乐观情景）
A6: 定价·体验包（元） | B6: 29.9 | C6: 单次启动包
A7: 定价·月度会员（元） | B7: 99 | C7: AI 合伙人
A8: 定价·年度会员（元） | B8: 599 | C8: 创业全程陪跑
A11: 行业基准（供对照）
A12: 消费端 AI 付费转化率 | B12: 9.2% | C12: a16z 第七版，全球口径；企业端为 45%
A13: AI 应用年度留存率 | B13: 21.1% | C13: RevenueCat 2026；非 AI 应用为 30.7%
A14: 独立开发者月入 <1000 美元占比 | B14: 85% | C14: Indie Hackers 2026
A15: 从开始到月入 1000 美元平均耗时 | B15: 8 个月 | C15: Indie Hackers 2026
A16: 小微经营者现金流维持时间 | B16: 2.9 个月 | C16: 北大《中国小微经营者调查》
A17: 失败项目死于「零用户」比例 | B17: 68% | C17: Stripe Atlas 2026，2000+ 独立开发者

Sheet 悲观情景
B1: 悲观情景 12 个月现金流推演
B2: 内容未起量，靠零星转发；转化率 1.5%；绝大多数只买 29.9 元体验包。对应约 85% 的独立开发者。
B3: 黄色格子可直接修改，其余为公式自动计算
B5: 月份 | C5: 月访客数 | D5: 付费转化率 | E5: 付费人数 | F5: 客单价(元) | G5: 月营收(元) | H5: 固定成本(元) | I5: 变动成本(元) | J5: 月成本(元) | K5: 月现金流(元) | L5: 累计现金流(元)
B6: 第 1 月 | C6: 200 | D6: 0.015 | E6: =ROUND(C6*D6,0) | F6: 40 | G6: =E6*F6 | H6: 1200 | I6: =E6*参数!$B$3 | J6: =H6+I6 | K6: =G6-J6 | L6: =SUM($K$6:K6)
B7: 第 2 月 | C7: 260 | D7: 0.015 | E7: =ROUND(C7*D7,0) | F7: 40 | G7: =E7*F7 | H7: 1200 | I7: =E7*参数!$B$3 | J7: =H7+I7 | K7: =G7-J7 | L7: =SUM($K$6:K7)
B8: 第 3 月 | C8: 350 | D8: 0.015 | E8: =ROUND(C8*D8,0) | F8: 40 | G8: =E8*F8 | H8: 1200 | I8: =E8*参数!$B$3 | J8: =H8+I8 | K8: =G8-J8 | L8: =SUM($K$6:K8)
B9: 第 4 月 | C9: 450 | D9: 0.015 | E9: =ROUND(C9*D9,0) | F9: 40 | G9: =E9*F9 | H9: 1200 | I9: =E9*参数!$B$3 | J9: =H9+I9 | K9: =G9-J9 | L9: =SUM($K$6:K9)
B10: 第 5 月 | C10: 560 | D10: 0.015 | E10: =ROUND(C10*D10,0) | F10: 40 | G10: =E10*F10 | H10: 1200 | I10: =E10*参数!$B$3 | J10: =H10+I10 | K10: =G10-J10 | L10: =SUM($K$6:K10)
B11: 第 6 月 | C11: 700 | D11: 0.015 | E11: =ROUND(C11*D11,0) | F11: 40 | G11: =E11*F11 | H11: 1200 | I11: =E11*参数!$B$3 | J11: =H11+I11 | K11: =G11-J11 | L11: =SUM($K$6:K11)
B12: 第 7 月 | C12: 820 | D12: 0.015 | E12: =ROUND(C12*D12,0) | F12: 40 | G12: =E12*F12 | H12: 1200 | I12: =E12*参数!$B$3 | J12: =H12+I12 | K12: =G12-J12 | L12: =SUM($K$6:K12)
B13: 第 8 月 | C13: 950 | D13: 0.015 | E13: =ROUND(C13*D13,0) | F13: 40 | G13: =E13*F13 | H13: 1200 | I13: =E13*参数!$B$3 | J13: =H13+I13 | K13: =G13-J13 | L13: =SUM($K$6:K13)
B14: 第 9 月 | C14: 1050 | D14: 0.015 | E14: =ROUND(C14*D14,0) | F14: 40 | G14: =E14*F14 | H14: 1200 | I14: =E14*参数!$B$3 | J14: =H14+I14 | K14: =G14-J14 | L14: =SUM($K$6:K14)
B15: 第 10 月 | C15: 1130 | D15: 0.015 | E15: =ROUND(C15*D15,0) | F15: 40 | G15: =E15*F15 | H15: 1200 | I15: =E15*参数!$B$3 | J15: =H15+I15 | K15: =G15-J15 | L15: =SUM($K$6:K15)
B16: 第 11 月 | C16: 1180 | D16: 0.015 | E16: =ROUND(C16*D16,0) | F16: 40 | G16: =E16*F16 | H16: 1200 | I16: =E16*参数!$B$3 | J16: =H16+I16 | K16: =G16-J16 | L16: =SUM($K$6:K16)
B17: 第 12 月 | C17: 1200 | D17: 0.015 | E17: =ROUND(C17*D17,0) | F17: 40 | G17: =E17*F17 | H17: 1200 | I17: =E17*参数!$B$3 | J17: =H17+I17 | K17: =G17-J17 | L17: =SUM($K$6:K17)
B18: 全年合计 | E18: =SUM(E6:E17) | G18: =SUM(G6:G17) | J18: =SUM(J6:J17) | K18: =SUM(K6:K17)
B20: 结论 | C20: ="首年总营收 "&TEXT(G18,"#,##0")&" 元 ｜ 首年净现金流 "&TEXT(K18,"#,##0")&" 元"
C21: ="累计现金流转正时点："&IF(COUNTIF(L6:L17,">0")=0,"始终为负",INDEX(B6:B17,MATCH(TRUE,INDEX(L6:L17>0,0),0))&"（第 "&MATCH(TRUE,INDEX(L6:L17>0,0),0)&" 个月）")

Sheet 中性情景
B1: 中性情景 12 个月现金流推演
B2: 内容稳定产出（每周 2—3 篇），裂变开始起作用；转化率 2.2%；部分用户升级月卡。对应约 10%。
B3: 黄色格子可直接修改，其余为公式自动计算
B5: 月份 | C5: 月访客数 | D5: 付费转化率 | E5: 付费人数 | F5: 客单价(元) | G5: 月营收(元) | H5: 固定成本(元) | I5: 变动成本(元) | J5: 月成本(元) | K5: 月现金流(元) | L5: 累计现金流(元)
B6: 第 1 月 | C6: 400 | D6: 0.022 | E6: =ROUND(C6*D6,0) | F6: 55 | G6: =E6*F6 | H6: 1200 | I6: =E6*参数!$B$3 | J6: =H6+I6 | K6: =G6-J6 | L6: =SUM($K$6:K6)
B7: 第 2 月 | C7: 520 | D7: 0.022 | E7: =ROUND(C7*D7,0) | F7: 55 | G7: =E7*F7 | H7: 1200 | I7: =E7*参数!$B$3 | J7: =H7+I7 | K7: =G7-J7 | L7: =SUM($K$6:K7)
B8: 第 3 月 | C8: 650 | D8: 0.022 | E8: =ROUND(C8*D8,0) | F8: 55 | G8: =E8*F8 | H8: 1200 | I8: =E8*参数!$B$3 | J8: =H8+I8 | K8: =G8-J8 | L8: =SUM($K$6:K8)
B9: 第 4 月 | C9: 900 | D9: 0.022 | E9: =ROUND(C9*D9,0) | F9: 55 | G9: =E9*F9 | H9: 1200 | I9: =E9*参数!$B$3 | J9: =H9+I9 | K9: =G9-J9 | L9: =SUM($K$6:K9)
B10: 第 5 月 | C10: 1150 | D10: 0.022 | E10: =ROUND(C10*D10,0) | F10: 55 | G10: =E10*F10 | H10: 1200 | I10: =E10*参数!$B$3 | J10: =H10+I10 | K10: =G10-J10 | L10: =SUM($K$6:K10)
B11: 第 6 月 | C11: 1800 | D11: 0.022 | E11: =ROUND(C11*D11,0) | F11: 55 | G11: =E11*F11 | H11: 1200 | I11: =E11*参数!$B$3 | J11: =H11+I11 | K11: =G11-J11 | L11: =SUM($K$6:K11)
B12: 第 7 月 | C12: 2100 | D12: 0.022 | E12: =ROUND(C12*D12,0) | F12: 55 | G12: =E12*F12 | H12: 1200 | I12: =E12*参数!$B$3 | J12: =H12+I12 | K12: =G12-J12 | L12: =SUM($K$6:K12)
B13: 第 8 月 | C13: 2350 | D13: 0.022 | E13: =ROUND(C13*D13,0) | F13: 55 | G13: =E13*F13 | H13: 1200 | I13: =E13*参数!$B$3 | J13: =H13+I13 | K13: =G13-J13 | L13: =SUM($K$6:K13)
B14: 第 9 月 | C14: 2600 | D14: 0.022 | E14: =ROUND(C14*D14,0) | F14: 55 | G14: =E14*F14 | H14: 1200 | I14: =E14*参数!$B$3 | J14: =H14+I14 | K14: =G14-J14 | L14: =SUM($K$6:K14)
B15: 第 10 月 | C15: 2900 | D15: 0.022 | E15: =ROUND(C15*D15,0) | F15: 55 | G15: =E15*F15 | H15: 1200 | I15: =E15*参数!$B$3 | J15: =H15+I15 | K15: =G15-J15 | L15: =SUM($K$6:K15)
B16: 第 11 月 | C16: 3200 | D16: 0.022 | E16: =ROUND(C16*D16,0) | F16: 55 | G16: =E16*F16 | H16: 1200 | I16: =E16*参数!$B$3 | J16: =H16+I16 | K16: =G16-J16 | L16: =SUM($K$6:K16)
B17: 第 12 月 | C17: 3500 | D17: 0.022 | E17: =ROUND(C17*D17,0) | F17: 55 | G17: =E17*F17 | H17: 1200 | I17: =E17*参数!$B$3 | J17: =H17+I17 | K17: =G17-J17 | L17: =SUM($K$6:K17)
B18: 全年合计 | E18: =SUM(E6:E17) | G18: =SUM(G6:G17) | J18: =SUM(J6:J17) | K18: =SUM(K6:K17)
B20: 结论 | C20: ="首年总营收 "&TEXT(G18,"#,##0")&" 元 ｜ 首年净现金流 "&TEXT(K18,"#,##0")&" 元"
C21: ="累计现金流转正时点："&IF(COUNTIF(L6:L17,">0")=0,"始终为负",INDEX(B6:B17,MATCH(TRUE,INDEX(L6:L17>0,0),0))&"（第 "&MATCH(TRUE,INDEX(L6:L17>0,0),0)&" 个月）")

Sheet 乐观情景
B1: 乐观情景 12 个月现金流推演
B2: 内容起量 + 裂变飞轮转起来；转化率 3.5%；第 7 个月起加大投入。对应约 3%—5%。
B3: 黄色格子可直接修改，其余为公式自动计算
B5: 月份 | C5: 月访客数 | D5: 付费转化率 | E5: 付费人数 | F5: 客单价(元) | G5: 月营收(元) | H5: 固定成本(元) | I5: 变动成本(元) | J5: 月成本(元) | K5: 月现金流(元) | L5: 累计现金流(元)
B6: 第 1 月 | C6: 600 | D6: 0.035 | E6: =ROUND(C6*D6,0) | F6: 70 | G6: =E6*F6 | H6: 1200 | I6: =E6*参数!$B$3 | J6: =H6+I6 | K6: =G6-J6 | L6: =SUM($K$6:K6)
B7: 第 2 月 | C7: 900 | D7: 0.035 | E7: =ROUND(C7*D7,0) | F7: 70 | G7: =E7*F7 | H7: 1200 | I7: =E7*参数!$B$3 | J7: =H7+I7 | K7: =G7-J7 | L7: =SUM($K$6:K7)
B8: 第 3 月 | C8: 1400 | D8: 0.035 | E8: =ROUND(C8*D8,0) | F8: 70 | G8: =E8*F8 | H8: 1200 | I8: =E8*参数!$B$3 | J8: =H8+I8 | K8: =G8-J8 | L8: =SUM($K$6:K8)
B9: 第 4 月 | C9: 2100 | D9: 0.035 | E9: =ROUND(C9*D9,0) | F9: 70 | G9: =E9*F9 | H9: 1200 | I9: =E9*参数!$B$3 | J9: =H9+I9 | K9: =G9-J9 | L9: =SUM($K$6:K9)
B10: 第 5 月 | C10: 3000 | D10: 0.035 | E10: =ROUND(C10*D10,0) | F10: 70 | G10: =E10*F10 | H10: 1200 | I10: =E10*参数!$B$3 | J10: =H10+I10 | K10: =G10-J10 | L10: =SUM($K$6:K10)
B11: 第 6 月 | C11: 4200 | D11: 0.035 | E11: =ROUND(C11*D11,0) | F11: 70 | G11: =E11*F11 | H11: 1200 | I11: =E11*参数!$B$3 | J11: =H11+I11 | K11: =G11-J11 | L11: =SUM($K$6:K11)
B12: 第 7 月 | C12: 5600 | D12: 0.035 | E12: =ROUND(C12*D12,0) | F12: 70 | G12: =E12*F12 | H12: 3500 | I12: =E12*参数!$B$3 | J12: =H12+I12 | K12: =G12-J12 | L12: =SUM($K$6:K12)
B13: 第 8 月 | C13: 7000 | D13: 0.035 | E13: =ROUND(C13*D13,0) | F13: 70 | G13: =E13*F13 | H13: 3500 | I13: =E13*参数!$B$3 | J13: =H13+I13 | K13: =G13-J13 | L13: =SUM($K$6:K13)
B14: 第 9 月 | C14: 8300 | D14: 0.035 | E14: =ROUND(C14*D14,0) | F14: 70 | G14: =E14*F14 | H14: 3500 | I14: =E14*参数!$B$3 | J14: =H14+I14 | K14: =G14-J14 | L14: =SUM($K$6:K14)
B15: 第 10 月 | C15: 9500 | D15: 0.035 | E15: =ROUND(C15*D15,0) | F15: 70 | G15: =E15*F15 | H15: 3500 | I15: =E15*参数!$B$3 | J15: =H15+I15 | K15: =G15-J15 | L15: =SUM($K$6:K15)
B16: 第 11 月 | C16: 10800 | D16: 0.035 | E16: =ROUND(C16*D16,0) | F16: 70 | G16: =E16*F16 | H16: 3500 | I16: =E16*参数!$B$3 | J16: =H16+I16 | K16: =G16-J16 | L16: =SUM($K$6:K16)
B17: 第 12 月 | C17: 12000 | D17: 0.035 | E17: =ROUND(C17*D17,0) | F17: 70 | G17: =E17*F17 | H17: 3500 | I17: =E17*参数!$B$3 | J17: =H17+I17 | K17: =G17-J17 | L17: =SUM($K$6:K17)
B18: 全年合计 | E18: =SUM(E6:E17) | G18: =SUM(G6:G17) | J18: =SUM(J6:J17) | K18: =SUM(K6:K17)
B20: 结论 | C20: ="首年总营收 "&TEXT(G18,"#,##0")&" 元 ｜ 首年净现金流 "&TEXT(K18,"#,##0")&" 元"
C21: ="累计现金流转正时点："&IF(COUNTIF(L6:L17,">0")=0,"始终为负",INDEX(B6:B17,MATCH(TRUE,INDEX(L6:L17>0,0),0))&"（第 "&MATCH(TRUE,INDEX(L6:L17>0,0),0)&" 个月）")

Sheet 三情景对比
A1: 首年现金流三情景对比
A3: 对比项 | B3: 悲观情景 | C3: 中性情景 | D3: 乐观情景 | E3: 说明
A4: 对应人群占比 | B4: 85% | C4: 约 10% | D4: 约 3%—5% | E4: Indie Hackers 收入分布
A5: 年末月访客数 | B5: 1,200 | C5: 3,500 | D5: 12,000 | E5: 决定收入的第一变量
A6: 付费转化率 | B6: 1.5% | C6: 2.2% | D6: 3.5% | E6: 消费端基准 9.2%，首年现实值远低于此
A7: 客单价 ARPPU | B7: 40 元 | C7: 55 元 | D7: 70 元 | E7: 多数人只买 29.9 元体验包
A8: 年末月营收 | B8: 720 元 | C8: 4,235 元 | D8: 29,400 元
A9: 首年总营收 | B9: 约 5,320 元 | C9: 约 26,675 元 | D9: 约 160,370 元
A10: 首年净现金流 | B10: 约 -9,479 元 | C10: 约 +10,820 元 | D10: 约 +125,297 元
A11: 累计现金流转正时点 | B11: 始终为负 | C11: 第 7 个月 | D11: 第 1 个月
A12: 一句话结论 | B12: 活着但没赚到钱 | C12: 副业级收入 | D12: 做成了，但未暴富 | E12: 三档差别 100% 来自获客与转化

Sheet 打平计算器
A1: 每月需要多少访客才不亏钱
A2: 公式：月固定成本 ÷（客单价 × 转化率）＝ 每月打平所需访客
A4: 情景 | B4: 客单价(元) | C4: 转化率 | D4: 每月打平所需访客 | E4: 当前设定
A5: 悲观情景 | B5: 40 | C5: 0.015 | D5: =ROUND(参数!$B$4/(B5*C5),0) | E5: 月固定成本取参数表「基础」值
A6: 中性情景 | B6: 55 | C6: 0.022 | D6: =ROUND(参数!$B$4/(B6*C6),0) | E6: 月固定成本取参数表「基础」值
A7: 乐观情景 | B7: 70 | C7: 0.035 | D7: =ROUND(参数!$B$4/(B7*C7),0) | E7: 月固定成本取参数表「基础」值
A10: 读法：这是你的第一个经营目标，不是「做多少功能」。
A11: 一个月拿到 1,000 个真实访客，比多做一个功能重要得多。
